gd/share/__init__.py
gd/share/__main__.py
gd/share/main.py
gd/share/py.typed
gd/share/version.py
gd_share-1.0.1.dist-info/LICENSE
gd_share-1.0.1.dist-info/METADATA
gd_share-1.0.1.dist-info/WHEEL
gd_share-1.0.1.dist-info/entry_points.txt
gd_share-1.0.1.dist-info/RECORD
