Metadata-Version: 2.1
Name: gd-share
Version: 1.0.1
Summary: Sharing Geometry Dash levels through CLI.
Home-page: https://github.com/nekitdev/gd.share
License: MIT
Keywords: python,gd,share
Author: nekitdev
Requires-Python: >=3.7
Classifier: Development Status :: 4 - Beta
Classifier: Intended Audience :: Developers
Classifier: License :: OSI Approved :: MIT License
Classifier: Operating System :: OS Independent
Classifier: Programming Language :: Python :: 3
Classifier: Programming Language :: Python :: 3.7
Classifier: Programming Language :: Python :: 3.8
Classifier: Programming Language :: Python :: 3.9
Classifier: Programming Language :: Python :: 3.10
Classifier: Programming Language :: Python :: 3.11
Classifier: Typing :: Typed
Requires-Dist: entrypoint (>=1.4.0)
Requires-Dist: gd.py (>=1.0.0)
Requires-Dist: tabulate (>=0.9.0)
Project-URL: Documentation, https://nekitdev.github.io/gd.share
Project-URL: Discord, https://nekit.dev/discord
Project-URL: Funding, https://patreon.com/nekitdev
Project-URL: Issues, https://github.com/nekitdev/gd.share/issues
Project-URL: Repository, https://github.com/nekitdev/gd.share
